<?xml version="1.0" encoding="utf-8" ?>
<dwsync>
<file name="arrow.png" server="162.210.101.140/lumalu.us/" local="130476478456034764" remote="130464204600000000" Dst="2" />
<file name="c1.png" server="162.210.101.140/lumalu.us/" local="130476478465270895" remote="130464204600000000" Dst="2" />
<file name="avatar.png" server="162.210.101.140/lumalu.us/" local="130476478465280901" remote="130464204600000000" Dst="2" />
<file name="c3.png" server="162.210.101.140/lumalu.us/" local="130476478473016022" remote="130464204600000000" Dst="2" />
<file name="banner3.jpg" server="162.210.101.140/lumalu.us/" local="130476478473026028" remote="130464204600000000" Dst="2" />
<file name="c2.png" server="162.210.101.140/lumalu.us/" local="130476478473026028" remote="130464204600000000" Dst="2" />
<file name="gallery.png" server="162.210.101.140/lumalu.us/" local="130476478483736071" remote="130464204600000000" Dst="2" />
<file name="contact.jpg" server="162.210.101.140/lumalu.us/" local="130476478483746073" remote="130464204600000000" Dst="2" />
<file name="c4.png" server="162.210.101.140/lumalu.us/" local="130476478483756080" remote="130464204600000000" Dst="2" />
<file name="heart.png" server="162.210.101.140/lumalu.us/" local="130476478494553227" remote="130464204600000000" Dst="2" />
<file name="left.png" server="162.210.101.140/lumalu.us/" local="130476478494573223" remote="130464204600000000" Dst="2" />
<file name="lock.png" server="162.210.101.140/lumalu.us/" local="130476478503569196" remote="130464204600000000" Dst="2" />
<file name="header-bg.jpg" server="162.210.101.140/lumalu.us/" local="130476478503579202" remote="130464204600000000" Dst="2" />
<file name="logo copy.png" server="162.210.101.140/lumalu.us/" local="130476478503619224" remote="130464204600000000" Dst="2" />
<file name="logo.png" server="162.210.101.140/lumalu.us/" local="130476478514356336" remote="130464204600000000" Dst="2" />
<file name="point.png" server="162.210.101.140/lumalu.us/" local="130476478514526727" remote="130464204600000000" Dst="2" />
<file name="news.jpg" server="162.210.101.140/lumalu.us/" local="130476478514766894" remote="130464204600000000" Dst="2" />
<file name="port.jpg" server="162.210.101.140/lumalu.us/" local="130476478525103805" remote="130464204600000000" Dst="2" />
<file name="port1.jpg" server="162.210.101.140/lumalu.us/" local="130476478525424017" remote="130464204600000000" Dst="2" />
<file name="port10.jpg" server="162.210.101.140/lumalu.us/" local="130476478533001837" remote="130464204600000000" Dst="2" />
<file name="port11.jpg" server="162.210.101.140/lumalu.us/" local="130476478533242291" remote="130464204600000000" Dst="2" />
<file name="port12.jpg" server="162.210.101.140/lumalu.us/" local="130476478540757257" remote="130464204600000000" Dst="2" />
<file name="port13.jpg" server="162.210.101.140/lumalu.us/" local="130476478545650501" remote="130464204600000000" Dst="2" />
<file name="port12.png" server="162.210.101.140/lumalu.us/" local="130476478545650501" remote="130464204600000000" Dst="2" />
<file name="port14.jpg" server="162.210.101.140/lumalu.us/" local="130476478550303594" remote="130464204600000000" Dst="2" />
<file name="port2.jpg" server="162.210.101.140/lumalu.us/" local="130476478556597760" remote="130464204600000000" Dst="2" />
<file name="port15.jpg" server="162.210.101.140/lumalu.us/" local="130476478556757858" remote="130464204600000000" Dst="2" />
<file name="port3.jpg" server="162.210.101.140/lumalu.us/" local="130476478564252828" remote="130464204600000000" Dst="2" />
<file name="port4.jpg" server="162.210.101.140/lumalu.us/" local="130476478568975946" remote="130464204600000000" Dst="2" />
<file name="port5.jpg" server="162.210.101.140/lumalu.us/" local="130476478568985944" remote="130464204600000000" Dst="2" />
<file name="port6.jpg" server="162.210.101.140/lumalu.us/" local="130476478576610995" remote="130464204600000000" Dst="2" />
<file name="port7.jpg" server="162.210.101.140/lumalu.us/" local="130476478576620998" remote="130464204600000000" Dst="2" />
<file name="port8.jpg" server="162.210.101.140/lumalu.us/" local="130476478584316096" remote="130464204600000000" Dst="2" />
<file name="port9.jpg" server="162.210.101.140/lumalu.us/" local="130476478584316096" remote="130464204600000000" Dst="2" />
<file name="port9 .jpg" server="162.210.101.140/lumalu.us/" local="130476478592061227" remote="130464204600000000" Dst="2" />
<file name="right.png" server="162.210.101.140/lumalu.us/" local="130476478592061227" remote="130464204600000000" Dst="2" />
<file name="socil.png" server="162.210.101.140/lumalu.us/" local="130476478592612438" remote="130464204600000000" Dst="2" />
<file name="top.jpg" server="162.210.101.140/lumalu.us/" local="130476478603039345" remote="130464204600000000" Dst="2" />
<file name="tag.png" server="162.210.101.140/lumalu.us/" local="130476478603049351" remote="130464204600000000" Dst="2" />
<file name="top1.jpg" server="162.210.101.140/lumalu.us/" local="130476478603119389" remote="130464204600000000" Dst="2" />
<file name="top_move.png" server="162.210.101.140/lumalu.us/" local="130476478613896540" remote="130464204600000000" Dst="2" />
<file name="top1.png" server="162.210.101.140/lumalu.us/" local="130476478613906539" remote="130464204600000000" Dst="2" />
<file name="zoom.png" server="162.210.101.140/lumalu.us/" local="130476478613916605" remote="130464204600000000" Dst="2" />
</dwsync>